eodms_rapi/__init__.py
eodms_rapi/__version__.py
eodms_rapi/eodms.py
eodms_rapi/geo.py
eodms_rapi/query_error.py
eodms_rapi/rapi_requests.py
py_eodms_rapi-1.10.4.dist-info/LICENSE
py_eodms_rapi-1.10.4.dist-info/METADATA
py_eodms_rapi-1.10.4.dist-info/WHEEL
py_eodms_rapi-1.10.4.dist-info/top_level.txt
py_eodms_rapi-1.10.4.dist-info/RECORD
