Metadata-Version: 2.1
Name: py-eodms-rapi
Version: 1.10.4
Summary: EODMS RAPI Client is a Python3 package used to access the REST API service provided by the Earth Observation Data Management System (EODMS) from Natural Resources Canada.
Home-page: https://py-eodms-rapi.readthedocs.io/en/latest/
Author: Kevin Ballantyne (Natural Resources Canada)
Author-email: kevin.ballantyne@nrcan-rncan.gc.ca
License: LICENSE
Project-URL: Source, https://github.com/eodms-sgdot/py-eodms-rapi
Project-URL: Bug Tracker, https://github.com/eodms-sgdot/py-eodms-rapi/issues
Classifier: Programming Language :: Python :: 3
Classifier: License :: OSI Approved :: MIT License
Classifier: Operating System :: OS Independent
Requires-Python: >=3.6
License-File: LICENSE
Requires-Dist: dateparser
Requires-Dist: requests
Requires-Dist: tqdm
Requires-Dist: geomet
Requires-Dist: lxml
